[
  {
    "points": 111.3,
    "players": [
      "1264",
      "1466",
      "2382",
      "3157",
      "3161",
      "3198",
      "3321",
      "4068",
      "4149",
      "4199",
      "4881",
      "515",
      "5917",
      "6945",
      "TB"
    ],
    "roster_id": 1,
    "custom_points": null,
    "matchup_id": 6,
    "starters": [
      "4881",
      "3198",
      "4199",
      "3321",
      "3157",
      "1466",
      "6945",
      "1264",
      "TB"
    ],
    "starters_points": [
      18.6,
      6.8,
      7.9,
      24.1,
      16,
      15.9,
      9.5,
      7.8,
      4.7
    ],
    "players_points": {
      "515": 0.2,
      "1264": 7.8,
      "1466": 15.9,
      "2382": 11.3,
      "3157": 16,
      "3161": 0,
      "3198": 6.8,
      "3321": 24.1,
      "4068": 8.1,
      "4149": 0,
      "4199": 7.9,
      "4881": 18.6,
      "5917": 4.8,
      "6945": 9.5,
      "TB": 4.7
    }
  },
  {
    "points": 118.86,
    "players": [
      "17",
      "1825",
      "2374",
      "3163",
      "3328",
      "4029",
      "4040",
      "421",
      "4455",
      "4663",
      "4983",
      "5844",
      "5890",
      "5980",
      "5987",
      "954",
      "BAL"
    ],
    "roster_id": 2,
    "custom_points": null,
    "matchup_id": 5,
    "starters": [
      "954",
      "5890",
      "4029",
      "4983",
      "2374",
      "5844",
      "4040",
      "17",
      "BAL"
    ],
    "starters_points": [
      24.56,
      7.1,
      37.2,
      1.8,
      4,
      9.9,
      15.3,
      9.5,
      9.5
    ],
    "players_points": {
      "17": 9.5,
      "421": 8.44,
      "954": 24.56,
      "1825": 0,
      "2374": 4,
      "3163": 0,
      "3328": 0,
      "4029": 37.2,
      "4040": 15.3,
      "4455": 0,
      "4663": 0,
      "4983": 1.8,
      "5844": 9.9,
      "5890": 7.1,
      "5980": 0,
      "5987": 6.9,
      "BAL": 9.5
    }
  },
  {
    "points": 97.54,
    "players": [
      "1067",
      "2216",
      "2319",
      "3664",
      "4017",
      "4227",
      "4981",
      "5012",
      "5185",
      "6783",
      "6820",
      "6845",
      "7045",
      "956",
      "GB"
    ],
    "roster_id": 3,
    "custom_points": null,
    "matchup_id": 1,
    "starters": [
      "4017",
      "6820",
      "6845",
      "2216",
      "1067",
      "5012",
      "6783",
      "4227",
      "GB"
    ],
    "starters_points": [
      24.24,
      9.4,
      10.8,
      6.4,
      10.3,
      2.2,
      18.5,
      11.4,
      4.3
    ],
    "players_points": {
      "956": 0,
      "1067": 10.3,
      "2216": 6.4,
      "2319": 6.4,
      "3664": 8.2,
      "4017": 24.24,
      "4227": 11.4,
      "4981": 0,
      "5012": 2.2,
      "5185": 0,
      "6783": 18.5,
      "6820": 9.4,
      "6845": 10.8,
      "7045": 5.9,
      "GB": 4.3
    }
  },
  {
    "points": 65.5,
    "players": [
      "1234",
      "1352",
      "2309",
      "2391",
      "391",
      "3969",
      "4018",
      "4217",
      "4993",
      "5170",
      "5248",
      "5937",
      "6007",
      "6130",
      "6931",
      "ARI"
    ],
    "roster_id": 4,
    "custom_points": null,
    "matchup_id": 3,
    "starters": [
      "1234",
      "2391",
      "6931",
      "2309",
      "5937",
      "4993",
      "3969",
      "391",
      "ARI"
    ],
    "starters_points": [
      22.1,
      1.6,
      9.9,
      7.5,
      8.1,
      4.2,
      4.1,
      4.8,
      3.2
    ],
    "players_points": {
      "391": 4.8,
      "1234": 22.1,
      "1352": 0,
      "2309": 7.5,
      "2391": 1.6,
      "3969": 4.1,
      "4018": 0,
      "4217": 0,
      "4993": 4.2,
      "5170": 2.3,
      "5248": 7.4,
      "5937": 8.1,
      "6007": 0,
      "6130": 3.4,
      "6931": 9.9,
      "ARI": 3.2
    }
  },
  {
    "points": 110.4,
    "players": [
      "1149",
      "1992",
      "2431",
      "4034",
      "4950",
      "4951",
      "4973",
      "5095",
      "5848",
      "5916",
      "6813",
      "830",
      "96",
      "HOU",
      "PHI"
    ],
    "roster_id": 5,
    "custom_points": null,
    "matchup_id": 4,
    "starters": [
      "96",
      "4034",
      "6813",
      "1992",
      "5848",
      "4973",
      "4950",
      "5095",
      "HOU"
    ],
    "starters_points": [
      28.9,
      27.1,
      7.4,
      8.1,
      3.8,
      6.2,
      18.3,
      7.1,
      3.5
    ],
    "players_points": {
      "96": 28.9,
      "830": 0,
      "1149": 0,
      "1992": 8.1,
      "2431": 3.7,
      "4034": 27.1,
      "4950": 18.3,
      "4951": 20.6,
      "4973": 6.2,
      "5095": 7.1,
      "5848": 3.8,
      "5916": 0,
      "6813": 7.4,
      "HOU": 3.5,
      "PHI": 0
    }
  },
  {
    "points": 96.6,
    "players": [
      "1387",
      "1408",
      "1848",
      "2168",
      "2449",
      "3214",
      "3306",
      "3934",
      "4892",
      "4984",
      "5230",
      "538",
      "574",
      "5892",
      "5927",
      "5947",
      "5967",
      "6059",
      "6153",
      "7090",
      "NO"
    ],
    "roster_id": 6,
    "custom_points": null,
    "matchup_id": 5,
    "starters": [
      "4984",
      "5967",
      "5892",
      "2449",
      "5927",
      "3214",
      "1408",
      "5230",
      "NO"
    ],
    "starters_points": [
      36,
      5.8,
      2.2,
      11.8,
      17.5,
      3.3,
      0.3,
      9.5,
      10.2
    ],
    "players_points": {
      "538": 9.8,
      "574": 0,
      "1387": 12.7,
      "1408": 0.3,
      "1848": 2.4,
      "2168": 0,
      "2449": 11.8,
      "3214": 3.3,
      "3306": 7.9,
      "3934": 0,
      "4892": 0,
      "4984": 36,
      "5230": 9.5,
      "5892": 2.2,
      "5927": 17.5,
      "5947": 16.9,
      "5967": 5.8,
      "6059": 0,
      "6153": 0.8,
      "7090": 4.3,
      "NO": 10.2
    }
  },
  {
    "points": 106.94,
    "players": [
      "1433",
      "1817",
      "2133",
      "2197",
      "2315",
      "2320",
      "2410",
      "367",
      "4602",
      "536",
      "5846",
      "6797",
      "6806",
      "6955",
      "KC"
    ],
    "roster_id": 7,
    "custom_points": null,
    "matchup_id": 3,
    "starters": [
      "6797",
      "6955",
      "2315",
      "2133",
      "5846",
      "367",
      "2320",
      "1433",
      "KC"
    ],
    "starters_points": [
      23.44,
      15.9,
      11.5,
      23.3,
      16.8,
      1,
      2.7,
      11.4,
      0.9
    ],
    "players_points": {
      "367": 1,
      "536": 3.1,
      "1433": 11.4,
      "1817": 0,
      "2133": 23.3,
      "2197": 14.3,
      "2315": 11.5,
      "2320": 2.7,
      "2410": 8.6,
      "4602": 0.5,
      "5846": 16.8,
      "6797": 23.44,
      "6806": 3.5,
      "6955": 15.9,
      "KC": 0.9
    }
  },
  {
    "points": 93.88,
    "players": [
      "1476",
      "1479",
      "1689",
      "3164",
      "3225",
      "3242",
      "4046",
      "4066",
      "5000",
      "5022",
      "5119",
      "5131",
      "6789",
      "6886",
      "NE"
    ],
    "roster_id": 8,
    "custom_points": null,
    "matchup_id": 2,
    "starters": [
      "4046",
      "5131",
      "5000",
      "1689",
      "6886",
      "4066",
      "1479",
      "5119",
      "NE"
    ],
    "starters_points": [
      31.48,
      0,
      8.8,
      3.8,
      7.3,
      10.8,
      16.3,
      14.6,
      0.8
    ],
    "players_points": {
      "1476": 4.2,
      "1479": 16.3,
      "1689": 3.8,
      "3164": 6.9,
      "3225": 0,
      "3242": 0,
      "4046": 31.48,
      "4066": 10.8,
      "5000": 8.8,
      "5022": 0,
      "5119": 14.6,
      "5131": 0,
      "6789": 1,
      "6886": 7.3,
      "NE": 0.8
    }
  },
  {
    "points": 50.06,
    "players": [
      "1386",
      "1426",
      "167",
      "2251",
      "3202",
      "4137",
      "5122",
      "59",
      "6149",
      "6151",
      "6790",
      "6798",
      "6801",
      "947",
      "IND",
      "WAS"
    ],
    "roster_id": 9,
    "custom_points": null,
    "matchup_id": 1,
    "starters": [
      "167",
      "4137",
      "6790",
      "947",
      "1426",
      "2251",
      "6149",
      "59",
      "WAS"
    ],
    "starters_points": [
      2.36,
      2,
      9.7,
      11.4,
      3,
      2.8,
      0.8,
      12.3,
      5.7
    ],
    "players_points": {
      "59": 12.3,
      "167": 2.36,
      "947": 11.4,
      "1386": 0,
      "1426": 3,
      "2251": 2.8,
      "3202": 0,
      "4137": 2,
      "5122": 0,
      "6149": 0.8,
      "6151": 0,
      "6790": 9.7,
      "6798": 0,
      "6801": 0,
      "IND": 6.7,
      "WAS": 5.7
    }
  },
  {
    "points": 79.74,
    "players": [
      "1144",
      "138",
      "2505",
      "2749",
      "3199",
      "3280",
      "4098",
      "4962",
      "4988",
      "5859",
      "5872",
      "6803",
      "6996",
      "7062",
      "PIT"
    ],
    "roster_id": 10,
    "custom_points": null,
    "matchup_id": 2,
    "starters": [
      "138",
      "3280",
      "6996",
      "5859",
      "1144",
      "2505",
      "3199",
      "7062",
      "PIT"
    ],
    "starters_points": [
      25.04,
      7.2,
      1.3,
      16.1,
      3.9,
      8.2,
      5.1,
      5.3,
      7.6
    ],
    "players_points": {
      "138": 25.04,
      "1144": 3.9,
      "2505": 8.2,
      "2749": 0,
      "3199": 5.1,
      "3280": 7.2,
      "4098": 0,
      "4962": 0,
      "4988": 0,
      "5859": 16.1,
      "5872": 0,
      "6803": 0,
      "6996": 1.3,
      "7062": 5.3,
      "PIT": 7.6
    }
  },
  {
    "points": 96.22,
    "players": [
      "184",
      "4037",
      "4039",
      "4131",
      "4144",
      "4351",
      "4666",
      "5100",
      "5849",
      "5850",
      "5857",
      "6786",
      "6938",
      "LAC",
      "LAR"
    ],
    "roster_id": 11,
    "custom_points": null,
    "matchup_id": 6,
    "starters": [
      "5849",
      "184",
      "5850",
      "6786",
      "4351",
      "5857",
      "4037",
      "4666",
      "LAC"
    ],
    "starters_points": [
      37.92,
      4.3,
      12.8,
      11.1,
      8.9,
      4.5,
      4.1,
      12.7,
      -0.1
    ],
    "players_points": {
      "184": 4.3,
      "4037": 4.1,
      "4039": 0,
      "4131": 0,
      "4144": 9.2,
      "4351": 8.9,
      "4666": 12.7,
      "5100": 3.8,
      "5849": 37.92,
      "5850": 12.8,
      "5857": 4.5,
      "6786": 11.1,
      "6938": 0,
      "LAC": -0.1,
      "LAR": 0
    }
  },
  {
    "points": 90.98,
    "players": [
      "1049",
      "2118",
      "2161",
      "2238",
      "2378",
      "2588",
      "289",
      "3423",
      "3678",
      "4035",
      "4036",
      "4273",
      "5052",
      "6794",
      "TEN"
    ],
    "roster_id": 12,
    "custom_points": null,
    "matchup_id": 4,
    "starters": [
      "289",
      "2161",
      "4035",
      "6794",
      "3423",
      "2118",
      "5052",
      "3678",
      "TEN"
    ],
    "starters_points": [
      22.68,
      12.8,
      10.9,
      6.4,
      6.3,
      8.2,
      1.8,
      8.6,
      13.3
    ],
    "players_points": {
      "289": 22.68,
      "1049": 14.62,
      "2118": 8.2,
      "2161": 12.8,
      "2238": 9.9,
      "2378": 0,
      "2588": 0,
      "3423": 6.3,
      "3678": 8.6,
      "4035": 10.9,
      "4036": 0,
      "4273": 0,
      "5052": 1.8,
      "6794": 6.4,
      "TEN": 13.3
    }
  }
]